LICENSE
citrus/__init__.py
citrus/__version__.py
citrus/core.py
citrus/errors.py
citrus/tests.py
citrus-0.0.5.dist-info/LICENSE
citrus-0.0.5.dist-info/WHEEL
citrus-0.0.5.dist-info/METADATA
citrus-0.0.5.dist-info/RECORD
