Metadata-Version: 2.1
Name: citrus
Version: 0.0.5
Summary: A more convenient interface to doing Binary Linear Programming with PuLP
Home-page: https://github.com/bgschiller/citrus
License: MIT
Keywords: pulp,linear,optimization
Author: Brian Schiller
Author-email: bgschiller@gmail.com
Requires-Python: >=3.6,<4.0
Classifier: License :: OSI Approved :: MIT License
Classifier: Programming Language :: Python
Classifier: Programming Language :: Python :: 3
Classifier: Programming Language :: Python :: 3.6
Classifier: Programming Language :: Python :: 3.7
Classifier: Programming Language :: Python :: 3.8
Classifier: Programming Language :: Python :: 3.9
Classifier: Programming Language :: Python :: 3.10
Classifier: Programming Language :: Python :: 3.11
Classifier: Programming Language :: Python :: 3
Classifier: Programming Language :: Python :: 3.6
Requires-Dist: pulp (>=2.0,<3.0)
Project-URL: Repository, https://github.com/bgschiller/citrus
